{
  "type_description_msg": {
    "type_description": {
      "type_name": "map_msgs/msg/ProjectedMapInfo",
      "fields": [
        {
          "name": "frame_id",
          "type": {
            "type_id": 17,
            "capacity": 0,
            "string_capacity": 0,
            "nested_type_name": ""
          },
          "default_value": ""
        },
        {
          "name": "x",
          "type": {
            "type_id": 11,
            "capacity": 0,
            "string_capacity": 0,
            "nested_type_name": ""
          },
          "default_value": ""
        },
        {
          "name": "y",
          "type": {
            "type_id": 11,
            "capacity": 0,
            "string_capacity": 0,
            "nested_type_name": ""
          },
          "default_value": ""
        },
        {
          "name": "width",
          "type": {
            "type_id": 11,
            "capacity": 0,
            "string_capacity": 0,
            "nested_type_name": ""
          },
          "default_value": ""
        },
        {
          "name": "height",
          "type": {
            "type_id": 11,
            "capacity": 0,
            "string_capacity": 0,
            "nested_type_name": ""
          },
          "default_value": ""
        },
        {
          "name": "min_z",
          "type": {
            "type_id": 11,
            "capacity": 0,
            "string_capacity": 0,
            "nested_type_name": ""
          },
          "default_value": ""
        },
        {
          "name": "max_z",
          "type": {
            "type_id": 11,
            "capacity": 0,
            "string_capacity": 0,
            "nested_type_name": ""
          },
          "default_value": ""
        }
      ]
    },
    "referenced_type_descriptions": []
  },
  "type_hashes": [
    {
      "type_name": "map_msgs/msg/ProjectedMapInfo",
      "hash_string": "RIHS01_99f95792a7ed7a784566add925ce2ac13e61cdb14e1e6804ca8e3fe0a5baaf13"
    }
  ]
}